UNDron_matrix_julkN/rtl/wb_i2c/i2c_master.v
`define log2(n)   ((n) <= (1<<0)  ? 0 : (n)  <= (1<<1)  ? 1  :\
                   (n) <= (1<<2)  ? 2 : (n)  <= (1<<3)  ? 3  :\
                   (n) <= (1<<4)  ? 4 : (n)  <= (1<<5)  ? 5  :\
                   (n) <= (1<<6)  ? 6 : (n)  <= (1<<7)  ? 7  :\
                   (n) <= (1<<8)  ? 8 : (n)  <= (1<<9)  ? 9  :\
                   (n) <= (1<<10) ? 10 : (n) <= (1<<11) ? 11 :\
                   (n) <= (1<<12) ? 12 : (n) <= (1<<13) ? 13 :\
                   (n) <= (1<<14) ? 14 : (n) <= (1<<15) ? 15 :\
                   (n) <= (1<<16) ? 16 : (n) <= (1<<17) ? 17 :\
                   (n) <= (1<<18) ? 18 : (n) <= (1<<19) ? 19 :\
                   (n) <= (1<<20) ? 20 : (n) <= (1<<21) ? 21 :\
                   (n) <= (1<<22) ? 22 : (n) <= (1<<23) ? 23 :\
                   (n) <= (1<<24) ? 24 : (n) <= (1<<25) ? 25 :\
                   (n) <= (1<<26) ? 26 : (n) <= (1<<27) ? 27 :\
                   (n) <= (1<<28) ? 28 : (n) <= (1<<29) ? 29 :\
                   (n) <= (1<<30) ? 30 : (n) <= (1<<31) ? 31 : 32)

module i2c_master (clk, reset, ena, addr, rw, data_wr, busy, data_rd, ack_error, sda, scl);

/*
                   ____________
 clk     -------->|            |--------> busy                          |
 reset   -------->|            |--------> ack_error                     |CONTROL SIGNALS 
 ena     -------->|            |                                        |
                  | i2c_master |
 rw      -------->|            |--------> data_rd                       |
 addr    -------->|            |<-------> sda                           |DATA SIGNALS
 data_wr -------->|____________|<-------> scl                           |

*/

    input           clk, reset, ena, rw;
    input [6:0]     addr ;
    input [7:0]     data_wr;
    output reg      busy = 0, ack_error = 0;
    output reg [7:0]    data_rd;
    inout           sda, scl;
    
    parameter  input_clk = 50000000;
    parameter  bus_clk = 100000;
    localparam divider = (input_clk/bus_clk)/4;
    parameter  countWidth = `log2(divider*4);
    
    parameter ready     = 4'b0000;//0
    parameter start     = 4'b0001;//1
    parameter command   = 4'b0010;//2
    parameter slv_ack1  = 4'b0011;//3
    parameter wr        = 4'b0100;//4
    parameter rd        = 4'b0101;//5
    parameter slv_ack2  = 4'b0110;//6
    parameter mstr_ack  = 4'b0111;//7
    parameter stop      = 4'b1000;//8
    reg [3:0] state = ready;
    
    reg data_clk = 1'b0;
    reg data_clk_prev = 1'b0;
    reg scl_clk = 1'b0;
    reg scl_ena = 1'b0;
    reg sda_int = 1'b1;
    reg sda_ena_n = 1'b0;
    reg [7:0] addr_rw = 8'b0;
    reg [7:0] data_tx = 8'b0;
    reg [7:0] data_rx = 8'b0;
    
    reg stretch = 1'b0;
    
    integer bit_cnt;
    
    reg [countWidth-1:0] count = 0;  //Arreglar tamano del contador.
    
    always @(posedge clk, posedge reset) begin
        if(reset) begin
            stretch = 1'b0;
            count = 0;
        end
        else begin
            data_clk_prev = data_clk;
            if(count == ((divider*4)-1)) //Hay que REVISAR ESTA PARTE, FALTA EL STRECH
                count = 0;
            else
                count = count + {{(countWidth-1){1'b0}},1'b1};
            if(count>=0 && count<divider) begin
                scl_clk = 1'b0;
                data_clk = 1'b0;
            end 
            else if(count>=divider && count<divider*2) begin
                scl_clk = 1'b0;
                data_clk = 1'b1;
            end
            else if(count>=divider*2 && count<divider*3) begin
                scl_clk = 1'b1;
                if(scl == 1'b0)
                    stretch = 1'b1;
                else
                    stretch = 1'b0;
                    data_clk = 1'b1;
            end
            else begin
                scl_clk = 1'b1;
                data_clk = 1'b0;
            end
        end
    end
    
    always @(negedge clk, posedge reset) begin
        if(reset) begin
            state       <= ready;                //return to initial state
            busy        <= 1'b1;                 //indicate not available 
            scl_ena     <= 1'b0;                 //sets scl high impedance 
            sda_int     <= 1'b0;                 //sets sda high impedance 
            ack_error   <= 1'b0;                 //clear acknowledge error flag 
            bit_cnt     <= 7;                    //restarts data bit counter 
            data_rd     <= 8'd0;                 //clear data read port 
        end
        else begin
            if(data_clk && ~data_clk_prev) begin
                case (state)
                    ready: begin    //0
                        if(ena) begin
                            busy <= 1'b1;                   //flag busy
                            addr_rw <= {addr,rw};          //collect requested slave address 
                            data_tx <= data_wr;            //collect requested data to write
                            state <= start;                //go to start bit
                        end

                        else begin
                            busy <= 1'b0;                   //unflag busy
                            state <= ready;                //remain idle
                        end


                    end
                    start: begin    //1
                            busy <= 1'b1;                     //resume busy if continuous mode
                            sda_int <= addr_rw[bit_cnt];     //set first address bit to bus
                            state <= command;                //go to command
                    end

                    command: begin  //2
                        if(bit_cnt==0) begin
                            sda_int <= 1'b1;                //release sda for slave acknowledge
                            bit_cnt <= 7;                  //reset bit counter for "byte" states
                            state <= slv_ack1;             //go to slave acknowledge (command)
                        end

                        else begin
                            bit_cnt <= bit_cnt - 1;        //keep track of transaction bits
                            sda_int <= addr_rw[bit_cnt-1]; //write address/command bit to bus
                            state <= command;              //continue with command
                        end
                    end

                    slv_ack1: begin //3
                        if(!addr_rw[0]) begin               //write command
                            sda_int <= data_tx[bit_cnt];    //write first bit of data
                            state <= wr;                    //go to write byte
                        end else begin                      
                            sda_int <= 1'b1;                 //release sda from incoming data
                            state <= rd;                    //go to read byte
                        end
                    end

                    wr: begin      //4                 //write byte of transaction
                        busy <= 1'b1;                     //resume busy if continuous mode
                        if(bit_cnt==1'b0) begin             //write byte transmit finished
                            sda_int <= 1'b1;                //release sda for slave acknowledge
                            bit_cnt <= 7;                  //reset bit counter for "byte" states
                            state <= slv_ack2;             //go to slave acknowledge (write)
                        end else begin                    //next clock cycle of write state
                            bit_cnt <= bit_cnt - 1;        //keep track of transaction bits
                            sda_int <= data_tx[bit_cnt-1]; //write next bit to bus
                            state <= wr;                   //continue writing
                        end
                    end

                    rd: begin      //5                   //read byte of transaction
                        busy <= 1'b1;                    //resume busy if continuous mode
                        if(bit_cnt == 0) begin             //read byte receive finished
                            if(ena && (addr_rw == {addr,rw})) begin  //continuing with anot
                                sda_int <= 1'b0;      //acknowledge the byte has bee
                            end else begin           //stopping or continuing with a write
                                sda_int <= 1'b1;      //send a no-acknowledge (before stop or
                            end
                            bit_cnt <= 7;                  //reset bit counter for "byte" states
                            data_rd <= data_rx;            //output received data
                            state <= mstr_ack;             //go to master acknowledge
                        end else begin                    //next clock cycle of read state
                            bit_cnt <= bit_cnt - 1;        //keep track of transaction bits
                            state <= rd;                   //continue reading
                        end
                    end

                    slv_ack2: begin//6                   //slave acknowledge bit (write)
                        if(ena) begin               //continue transaction
                            busy <= 1'b0;                   //continue is accepted
                            addr_rw <= {addr,rw};   //collect requested slave address and command
                            data_tx <= data_wr;            //collect requested data to write
                            if (addr_rw == {addr,rw}) begin //continue transaction with another
                                sda_int <= data_wr[bit_cnt]; //write first bit of data
                                state <= wr;                 //go to write byte
                            end else begin     //continue transaction with a read or new slave
                                state <= start;              //go to repeated start
                            end
                        end else begin                            //complete transaction
                            state <= stop;                 //go to stop bit
                        end
                    end

                    mstr_ack: begin //7                   //master acknowledge bit after a read
                        if(ena) begin               //continue transaction
                            busy <= 1'b0;    //continue is accepted and data received is avai
                            addr_rw <= {addr,rw};  //collect requested slave address and command
                            data_tx <= data_wr;            //collect requested data to write
                            if(addr_rw == {addr,rw}) begin   //continue transaction with anot
                                sda_int <= 1'b1;             //release sda from incoming data
                                state <= rd;                 //go to read byte
                            end else begin       //continue transaction with a write or new slave
                                state <= start;              //repeated start
                            end     
                        end else begin                             //complete transaction
                            state <= stop;                 //go to stop bit
                        end
                    end

                    stop: begin //8                      //stop bit of transaction
                        busy <= 1'b0;                     //unflag busy
                        state <= ready;                  //go to idle state
                    end
                endcase

            end else if (~data_clk && data_clk_prev) begin
                case (state)
                    start: begin
                        if(scl_ena == 1'b0) begin                  //starting new transaction
                            scl_ena <= 1'b1;                       //enable scl output
                            ack_error <= 1'b0;           //reset acknowledge error output
                        end
                    end
                    slv_ack1: begin             //receiving slave acknowledge (command)
                        if(sda != 1'b0 || ack_error) begin  //no-acknowledge or previous n
                            ack_error <= 1'b1;        //set error output if no-acknowledge
                        end
                    end
                    rd: begin                         //receiving slave data
                        data_rx[bit_cnt] <= sda;                //receive current slave data bit
                    end
                    slv_ack2: begin         //receiving slave acknowledge (write)
                        if (ena) begin
                           busy <= 1'b0;
                      
                            if(sda != 1'b0 || ack_error) begin  //no-acknowledge or previous 
                                ack_error <= 1'b1;         //set error output if no-acknowledge
                            end
                        end
                    end
                    stop: begin
                        scl_ena <= 1'b0;                         //disable scl
                    end
                    default: begin
                        scl_ena <= scl_ena;  //NULL
                    end
                endcase
            end
        end
    end
    
    always @(state, sda_int, data_clk, data_clk_prev) begin
        case(state)
            start:      sda_ena_n <= data_clk_prev;
            stop:       sda_ena_n <= !data_clk_prev;
            default:    sda_ena_n <= sda_int;
        endcase
    end
    
    assign scl = (scl_ena && ~scl_clk) ? 1'b0 : 1'bz;
    assign sda = (!sda_ena_n) ? 1'b0 : 1'bz;

    wire jackpot = (~data_clk && data_clk_prev);

endmodule

UNDron_matrix_ats/rtl/wb_i2c/i2c_master_TB.v
`timescale 10ns / 10ps
`define SIMULATION

module i2c_master_TB;
    reg           clk, reset, ena, rw;
    reg [6:0]     addr;
    reg [7:0]     data_wr;
    wire          busy, ack_error;
    wire [7:0]    data_rd;
    wire          sda, scl;
    reg           sda_out = 1'bz;
    reg  [4:0]    count_aux = 9;
    reg  [7:0]    vamo_a_leer = 8'h55;
    reg           direc = 1'b0;

    i2c_master inst1(clk, reset, ena, addr, rw, data_wr, busy, data_rd, ack_error, sda, scl);

    assign sda = sda_out;

    initial
        begin
            clk = 1'b0;
            reset = 1'b0;
            ena = 1'b0;
            rw = 1'b1;
            addr = 7'h58;
            data_wr = 8'hbf;
    end
    
    always #1 clk = ~clk; 


    
    always @(negedge scl) begin
       #251
       count_aux = count_aux-1;
        if (rw || !direc) begin 
             if (count_aux == 0) begin
                sda_out = 1'b0;
                data_wr = $random; 
                count_aux = 9;
                direc = 1'b1;
             end else begin
                sda_out = 1'bz;
             end
        end else begin
             if (count_aux == 0) begin
               sda_out = 1'bz;
               count_aux = 9;
               vamo_a_leer = data_wr;
             end else begin
               sda_out = vamo_a_leer[count_aux-1] ? 1'b1:1'b0;
            end
        end 
    end
      


   initial begin
     $dumpfile("i2c_master_TB.vcd");
     $dumpvars(-1, inst1);
      #10 
        reset = 1'b1;
      #10  
        reset = 1'b0;
      #1000 
        ena = 1'b1;
     #60000
     $finish;
   end

endmodule

UNDron_matrix_julkN/rtl/wb_i2c/simulation/i2c_master_TB.vcd
$date
	Wed Oct 26 10:51:14 2016
$end
$version
	Icarus Verilog
$end
$timescale
	10ps
$end
$scope module i2c_master_TB $end
$scope module inst1 $end
$var wire 7 ! addr [6:0] $end
$var wire 1 " clk $end
$var wire 8 # data_wr [7:0] $end
$var wire 1 $ ena $end
$var wire 1 % reset $end
$var wire 1 & rw $end
$var wire 1 ' scl $end
$var wire 1 ( sda $end
$var reg 1 ) ack_error $end
$var reg 8 * addr_rw [7:0] $end
$var integer 32 + bit_cnt [31:0] $end
$var reg 1 , busy $end
$var reg 10 - count [9:0] $end
$var reg 1 . data_clk $end
$var reg 1 / data_clk_prev $end
$var reg 8 0 data_rd [7:0] $end
$var reg 8 1 data_rx [7:0] $end
$var reg 8 2 data_tx [7:0] $end
$var reg 1 3 scl_clk $end
$var reg 1 4 scl_ena $end
$var reg 1 5 sda_ena_n $end
$var reg 1 6 sda_int $end
$var reg 4 7 state [3:0] $end
$var reg 1 8 stretch $end
$upscope $end
$upscope $end
$enddefinitions $end
#0
$dumpvars
08
b0 7
16
15
04
03
b0 2
b0 1
bx 0
0/
0.
b0 -
0,
bx +
b0 *
0)
z(
1'
1&
0%
0$
b10111111 #
0"
b1011000 !
$end
#1000
b1 -
1"
#2000
0"
#3000
b10 -
1"
#4000
0"
#5000
b11 -
1"
#6000
0"
#7000
b100 -
1"
#8000
0"
#9000
b101 -
1"
#10000
0(
05
b0 0
b111 +
06
1,
b0 -
0"
1%
#11000
1"
#12000
0"
#13000
1"
#14000
0"
#15000
1"
#16000
0"
#17000
1"
#18000
0"
#19000
1"
#20000
0"
0%
#21000
b1 -
1"
#22000
0"
#23000
b10 -
1"
#24000
0"
#25000
b11 -
1"
#26000
0"
#27000
b100 -
1"
#28000
0"
#29000
b101 -
1"
#30000
0"
#31000
b110 -
1"
#32000
0"
#33000
b111 -
1"
#34000
0"
#35000
b1000 -
1"
#36000
0"
#37000
b1001 -
1"
#38000
0"
#39000
b1010 -
1"
#40000
0"
#41000
b1011 -
1"
#42000
0"
#43000
b1100 -
1"
#44000
0"
#45000
b1101 -
1"
#46000
0"
#47000
b1110 -
1"
#48000
0"
#49000
b1111 -
1"
#50000
0"
#51000
b10000 -
1"
#52000
0"
#53000
b10001 -
1"
#54000
0"
#55000
b10010 -
1"
#56000
0"
#57000
b10011 -
1"
#58000
0"
#59000
b10100 -
1"
#60000
0"
#61000
b10101 -
1"
#62000
0"
#63000
b10110 -
1"
#64000
0"
#65000
b10111 -
1"
#66000
0"
#67000
b11000 -
1"
#68000
0"
#69000
b11001 -
1"
#70000
0"
#71000
b11010 -
1"
#72000
0"
#73000
b11011 -
1"
#74000
0"
#75000
b11100 -
1"
#76000
0"
#77000
b11101 -
1"
#78000
0"
#79000
b11110 -
1"
#80000
0"
#81000
b11111 -
1"
#82000
0"
#83000
b100000 -
1"
#84000
0"
#85000
b100001 -
1"
#86000
0"
#87000
b100010 -
1"
#88000
0"
#89000
b100011 -
1"
#90000
0"
#91000
b100100 -
1"
#92000
0"
#93000
b100101 -
1"
#94000
0"
#95000
b100110 -
1"
#96000
0"
#97000
b100111 -
1"
#98000
0"
#99000
b101000 -
1"
#100000
0"
#101000
b101001 -
1"
#102000
0"
#103000
b101010 -
1"
#104000
0"
#105000
b101011 -
1"
#106000
0"
#107000
b101100 -
1"
#108000
0"
#109000
b101101 -
1"
#110000
0"
#111000
b101110 -
1"
#112000
0"
#113000
b101111 -
1"
#114000
0"
#115000
b110000 -
1"
#116000
0"
#117000
b110001 -
1"
#118000
0"
#119000
b110010 -
1"
#120000
0"
#121000
b110011 -
1"
#122000
0"
#123000
b110100 -
1"
#124000
0"
#125000
b110101 -
1"
#126000
0"
#127000
b110110 -
1"
#128000
0"
#129000
b110111 -
1"
#130000
0"
#131000
b111000 -
1"
#132000
0"
#133000
b111001 -
1"
#134000
0"
#135000
b111010 -
1"
#136000
0"
#137000
b111011 -
1"
#138000
0"
#139000
b111100 -
1"
#140000
0"
#141000
b111101 -
1"
#142000
0"
#143000
b111110 -
1"
#144000
0"
#145000
b111111 -
1"
#146000
0"
#147000
b1000000 -
1"
#148000
0"
#149000
b1000001 -
1"
#150000
0"
#151000
b1000010 -
1"
#152000
0"
#153000
b1000011 -
1"
#154000
0"
#155000
b1000100 -
1"
#156000
0"
#157000
b1000101 -
1"
#158000
0"
#159000
b1000110 -
1"
#160000
0"
#161000
b1000111 -
1"
#162000
0"
#163000
b1001000 -
1"
#164000
0"
#165000
b1001001 -
1"
#166000
0"
#167000
b1001010 -
1"
#168000
0"
#169000
b1001011 -
1"
#170000
0"
#171000
b1001100 -
1"
#172000
0"
#173000
b1001101 -
1"
#174000
0"
#175000
b1001110 -
1"
#176000
0"
#177000
b1001111 -
1"
#178000
0"
#179000
b1010000 -
1"
#180000
0"
#181000
b1010001 -
1"
#182000
0"
#183000
b1010010 -
1"
#184000
0"
#185000
b1010011 -
1"
#186000
0"
#187000
b1010100 -
1"
#188000
0"
#189000
b1010101 -
1"
#190000
0"
#191000
b1010110 -
1"
#192000
0"
#193000
b1010111 -
1"
#194000
0"
#195000
b1011000 -
1"
#196000
0"
#197000
b1011001 -
1"
#198000
0"
#199000
b1011010 -
1"
#200000
0"
#201000
b1011011 -
1"
#202000
0"
#203000
b1011100 -
1"
#204000
0"
#205000
b1011101 -
1"
#206000
0"
#207000
b1011110 -
1"
#208000
0"
#209000
b1011111 -
1"
#210000
0"
#211000
b1100000 -
1"
#212000
0"
#213000
b1100001 -
1"
#214000
0"
#215000
b1100010 -
1"
#216000
0"
#217000
b1100011 -
1"
#218000
0"
#219000
b1100100 -
1"
#220000
0"
#221000
b1100101 -
1"
#222000
0"
#223000
b1100110 -
1"
#224000
0"
#225000
b1100111 -
1"
#226000
0"
#227000
b1101000 -
1"
#228000
0"
#229000
b1101001 -
1"
#230000
0"
#231000
b1101010 -
1"
#232000
0"
#233000
b1101011 -
1"
#234000
0"
#235000
b1101100 -
1"
#236000
0"
#237000
b1101101 -
1"
#238000
0"
#239000
b1101110 -
1"
#240000
0"
#241000
b1101111 -
1"
#242000
0"
#243000
b1110000 -
1"
#244000
0"
#245000
b1110001 -
1"
#246000
0"
#247000
b1110010 -
1"
#248000
0"
#249000
b1110011 -
1"
#250000
0"
#251000
b1110100 -
1"
#252000
0"
#253000
b1110101 -
1"
#254000
0"
#255000
b1110110 -
1"
#256000
0"
#257000
b1110111 -
1"
#258000
0"
#259000
b1111000 -
1"
#260000
0"
#261000
b1111001 -
1"
#262000
0"
#263000
b1111010 -
1"
#264000
0"
#265000
b1111011 -
1"
#266000
0"
#267000
b1111100 -
1"
#268000
0"
#269000
b1111101 -
1"
#270000
0"
#271000
b1111110 -
1"
#272000
0"
#273000
b1111111 -
1"
#274000
0"
#275000
b10000000 -
1"
#276000
0"
#277000
b10000001 -
1"
#278000
0"
#279000
b10000010 -
1"
#280000
0"
#281000
b10000011 -
1"
#282000
0"
#283000
b10000100 -
1"
#284000
0"
#285000
b10000101 -
1"
#286000
0"
#287000
b10000110 -
1"
#288000
0"
#289000
b10000111 -
1"
#290000
0"
#291000
b10001000 -
1"
#292000
0"
#293000
b10001001 -
1"
#294000
0"
#295000
b10001010 -
1"
#296000
0"
#297000
b10001011 -
1"
#298000
0"
#299000
b10001100 -
1"
#300000
0"
#301000
b10001101 -
1"
#302000
0"
#303000
b10001110 -
1"
#304000
0"
#305000
b10001111 -
1"
#306000
0"
#307000
b10010000 -
1"
#308000
0"
#309000
b10010001 -
1"
#310000
0"
#311000
b10010010 -
1"
#312000
0"
#313000
b10010011 -
1"
#314000
0"
#315000
b10010100 -
1"
#316000
0"
#317000
b10010101 -
1"
#318000
0"
#319000
b10010110 -
1"
#320000
0"
#321000
b10010111 -
1"
#322000
0"
#323000
b10011000 -
1"
#324000
0"
#325000
b10011001 -
1"
#326000
0"
#327000
b10011010 -
1"
#328000
0"
#329000
b10011011 -
1"
#330000
0"
#331000
b10011100 -
1"
#332000
0"
#333000
b10011101 -
1"
#334000
0"
#335000
b10011110 -
1"
#336000
0"
#337000
b10011111 -
1"
#338000
0"
#339000
b10100000 -
1"
#340000
0"
#341000
b10100001 -
1"
#342000
0"
#343000
b10100010 -
1"
#344000
0"
#345000
b10100011 -
1"
#346000
0"
#347000
b10100100 -
1"
#348000
0"
#349000
b10100101 -
1"
#350000
0"
#351000
b10100110 -
1"
#352000
0"
#353000
b10100111 -
1"
#354000
0"
#355000
b10101000 -
1"
#356000
0"
#357000
b10101001 -
1"
#358000
0"
#359000
b10101010 -
1"
#360000
0"
#361000
b10101011 -
1"
#362000
0"
#363000
b10101100 -
1"
#364000
0"
#365000
b10101101 -
1"
#366000
0"
#367000
b10101110 -
1"
#368000
0"
#369000
b10101111 -
1"
#370000
0"
#371000
b10110000 -
1"
#372000
0"
#373000
b10110001 -
1"
#374000
0"
#375000
b10110010 -
1"
#376000
0"
#377000
b10110011 -
1"
#378000
0"
#379000
b10110100 -
1"
#380000
0"
#381000
b10110101 -
1"
#382000
0"
#383000
b10110110 -
1"
#384000
0"
#385000
b10110111 -
1"
#386000
0"
#387000
b10111000 -
1"
#388000
0"
#389000
b10111001 -
1"
#390000
0"
#391000
b10111010 -
1"
#392000
0"
#393000
b10111011 -
1"
#394000
0"
#395000
b10111100 -
1"
#396000
0"
#397000
b10111101 -
1"
#398000
0"
#399000
b10111110 -
1"
#400000
0"
#401000
b10111111 -
1"
#402000
0"
#403000
b11000000 -
1"
#404000
0"
#405000
b11000001 -
1"
#406000
0"
#407000
b11000010 -
1"
#408000
0"
#409000
b11000011 -
1"
#410000
0"
#411000
b11000100 -
1"
#412000
0"
#413000
b11000101 -
1"
#414000
0"
#415000
b11000110 -
1"
#416000
0"
#417000
b11000111 -
1"
#418000
0"
#419000
b11001000 -
1"
#420000
0"
#421000
b11001001 -
1"
#422000
0"
#423000
b11001010 -
1"
#424000
0"
#425000
b11001011 -
1"
#426000
0"
#427000
b11001100 -
1"
#428000
0"
#429000
b11001101 -
1"
#430000
0"
#431000
b11001110 -
1"
#432000
0"
#433000
b11001111 -
1"
#434000
0"
#435000
b11010000 -
1"
#436000
0"
#437000
b11010001 -
1"
#438000
0"
#439000
b11010010 -
1"
#440000
0"
#441000
b11010011 -
1"
#442000
0"
#443000
b11010100 -
1"
#444000
0"
#445000
b11010101 -
1"
#446000
0"
#447000
b11010110 -
1"
#448000
0"
#449000
b11010111 -
1"
#450000
0"
#451000
b11011000 -
1"
#452000
0"
#453000
b11011001 -
1"
#454000
0"
#455000
b11011010 -
1"
#456000
0"
#457000
b11011011 -
1"
#458000
0"
#459000
b11011100 -
1"
#460000
0"
#461000
b11011101 -
1"
#462000
0"
#463000
b11011110 -
1"
#464000
0"
#465000
b11011111 -
1"
#466000
0"
#467000
b11100000 -
1"
#468000
0"
#469000
b11100001 -
1"
#470000
0"
#471000
b11100010 -
1"
#472000
0"
#473000
b11100011 -
1"
#474000
0"
#475000
b11100100 -
1"
#476000
0"
#477000
b11100101 -
1"
#478000
0"
#479000
b11100110 -
1"
#480000
0"
#481000
b11100111 -
1"
#482000
0"
#483000
b11101000 -
1"
#484000
0"
#485000
b11101001 -
1"
#486000
0"
#487000
b11101010 -
1"
#488000
0"
#489000
b11101011 -
1"
#490000
0"
#491000
b11101100 -
1"
#492000
0"
#493000
b11101101 -
1"
#494000
0"
#495000
b11101110 -
1"
#496000
0"
#497000
b11101111 -
1"
#498000
0"
#499000
b11110000 -
1"
#500000
0"
#501000
b11110001 -
1"
#502000
0"
#503000
b11110010 -
1"
#504000
0"
#505000
b11110011 -
1"
#506000
0"
#507000
b11110100 -
1"
#508000
0"
#509000
b11110101 -
1"
#510000
0"
#511000
b11110110 -
1"
#512000
0"
#513000
b11110111 -
1"
#514000
0"
#515000
b11111000 -
1"
#516000
0"
#517000
b11111001 -
1"
#518000
0"
#519000
1.
b11111010 -
1"
#520000
0,
0"
#521000
b11111011 -
1/
1"
#522000
0"
#523000
b11111100 -
1"
#524000
0"
#525000
b11111101 -
1"
#526000
0"
#527000
b11111110 -
1"
#528000
0"
#529000
b11111111 -
1"
#530000
0"
#531000
b100000000 -
1"
#532000
0"
#533000
b100000001 -
1"
#534000
0"
#535000
b100000010 -
1"
#536000
0"
#537000
b100000011 -
1"
#538000
0"
#539000
b100000100 -
1"
#540000
0"
#541000
b100000101 -
1"
#542000
0"
#543000
b100000110 -
1"
#544000
0"
#545000
b100000111 -
1"
#546000
0"
#547000
b100001000 -
1"
#548000
0"
#549000
b100001001 -
1"
#550000
0"
#551000
b100001010 -
1"
#552000
0"
#553000
b100001011 -
1"
#554000
0"
#555000
b100001100 -
1"
#556000
0"
#557000
b100001101 -
1"
#558000
0"
#559000
b100001110 -
1"
#560000
0"
#561000
b100001111 -
1"
#562000
0"
#563000
b100010000 -
1"
#564000
0"
#565000
b100010001 -
1"
#566000
0"
#567000
b100010010 -
1"
#568000
0"
#569000
b100010011 -
1"
#570000
0"
#571000
b100010100 -
1"
#572000
0"
#573000
b100010101 -
1"
#574000
0"
#575000
b100010110 -
1"
#576000
0"
#577000
b100010111 -
1"
#578000
0"
#579000
b100011000 -
1"
#580000
0"
#581000
b100011001 -
1"
#582000
0"
#583000
b100011010 -
1"
#584000
0"
#585000
b100011011 -
1"
#586000
0"
#587000
b100011100 -
1"
#588000
0"
#589000
b100011101 -
1"
#590000
0"
#591000
b100011110 -
1"
#592000
0"
#593000
b100011111 -
1"
#594000
0"
#595000
b100100000 -
1"
#596000
0"
#597000
b100100001 -
1"
#598000
0"
#599000
b100100010 -
1"
#600000
0"
#601000
b100100011 -
1"
#602000
0"
#603000
b100100100 -
1"
#604000
0"
#605000
b100100101 -
1"
#606000
0"
#607000
b100100110 -
1"
#608000
0"
#609000
b100100111 -
1"
#610000
0"
#611000
b100101000 -
1"
#612000
0"
#613000
b100101001 -
1"
#614000
0"
#615000
b100101010 -
1"
#616000
0"
#617000
b100101011 -
1"
#618000
0"
#619000
b100101100 -
1"
#620000
0"
#621000
b100101101 -
1"
#622000
0"
#623000
b100101110 -
1"
#624000
0"
#625000
b100101111 -
1"
#626000
0"
#627000
b100110000 -
1"
#628000
0"
#629000
b100110001 -
1"
#630000
0"
#631000
b100110010 -
1"
#632000
0"
#633000
b100110011 -
1"
#634000
0"
#635000
b100110100 -
1"
#636000
0"
#637000
b100110101 -
1"
#638000
0"
#639000
b100110110 -
1"
#640000
0"
#641000
b100110111 -
1"
#642000
0"
#643000
b100111000 -
1"
#644000
0"
#645000
b100111001 -
1"
#646000
0"
#647000
b100111010 -
1"
#648000
0"
#649000
b100111011 -
1"
#650000
0"
#651000
b100111100 -
1"
#652000
0"
#653000
b100111101 -
1"
#654000
0"
#655000
b100111110 -
1"
#656000
0"
#657000
b100111111 -
1"
#658000
0"
#659000
b101000000 -
1"
#660000
0"
#661000
b101000001 -
1"
#662000
0"
#663000
b101000010 -
1"
#664000
0"
#665000
b101000011 -
1"
#666000
0"
#667000
b101000100 -
1"
#668000
0"
#669000
b101000101 -
1"
#670000
0"
#671000
b101000110 -
1"
#672000
0"
#673000
b101000111 -
1"
#674000
0"
#675000
b101001000 -
1"
#676000
0"
#677000
b101001001 -
1"
#678000
0"
#679000
b101001010 -
1"
#680000
0"
#681000
b101001011 -
1"
#682000
0"
#683000
b101001100 -
1"
#684000
0"
#685000
b101001101 -
1"
#686000
0"
#687000
b101001110 -
1"
#688000
0"
#689000
b101001111 -
1"
#690000
0"
#691000
b101010000 -
1"
#692000
0"
#693000
b101010001 -
1"
#694000
0"
#695000
b101010010 -
1"
#696000
0"
#697000
b101010011 -
1"
#698000
0"
#699000
b101010100 -
1"
#700000
0"
#701000
b101010101 -
1"
#702000
0"
#703000
b101010110 -
1"
#704000
0"
#705000
b101010111 -
1"
#706000
0"
#707000
b101011000 -
1"
#708000
0"
#709000
b101011001 -
1"
#710000
0"
#711000
b101011010 -
1"
#712000
0"
#713000
b101011011 -
1"
#714000
0"
#715000
b101011100 -
1"
#716000
0"
#717000
b101011101 -
1"
#718000
0"
#719000
b101011110 -
1"
#720000
0"
#721000
b101011111 -
1"
#722000
0"
#723000
b101100000 -
1"
#724000
0"
#725000
b101100001 -
1"
#726000
0"
#727000
b101100010 -
1"
#728000
0"
#729000
b101100011 -
1"
#730000
0"
#731000
b101100100 -
1"
#732000
0"
#733000
b101100101 -
1"
#734000
0"
#735000
b101100110 -
1"
#736000
0"
#737000
b101100111 -
1"
#738000
0"
#739000
b101101000 -
1"
#740000
0"
#741000
b101101001 -
1"
#742000
0"
#743000
b101101010 -
1"
#744000
0"
#745000
b101101011 -
1"
#746000
0"
#747000
b101101100 -
1"
#748000
0"
#749000
b101101101 -
1"
#750000
0"
#751000
b101101110 -
1"
#752000
0"
#753000
b101101111 -
1"
#754000
0"
#755000
b101110000 -
1"
#756000
0"
#757000
b101110001 -
1"
#758000
0"
#759000
b101110010 -
1"
#760000
0"
#761000
b101110011 -
1"
#762000
0"
#763000
b101110100 -
1"
#764000
0"
#765000
b101110101 -
1"
#766000
0"
#767000
b101110110 -
1"
#768000
0"
#769000
b101110111 -
1"
#770000
0"
#771000
b101111000 -
1"
#772000
0"
#773000
b101111001 -
1"
#774000
0"
#775000
b101111010 -
1"
#776000
0"
#777000
b101111011 -
1"
#778000
0"
#779000
b101111100 -
1"
#780000
0"
#781000
b101111101 -
1"
#782000
0"
#783000
b101111110 -
1"
#784000
0"
#785000
b101111111 -
1"
#786000
0"
#787000
b110000000 -
1"
#788000
0"
#789000
b110000001 -
1"
#790000
0"
#791000
b110000010 -
1"
#792000
0"
#793000
b110000011 -
1"
#794000
0"
#795000
b110000100 -
1"
#796000
0"
#797000
b110000101 -
1"
#798000
0"
#799000
b110000110 -
1"
#800000
0"
#801000
b110000111 -
1"
#802000
0"
#803000
b110001000 -
1"
#804000
0"
#805000
b110001001 -
1"
#806000
0"
#807000
b110001010 -
1"
#808000
0"
#809000
b110001011 -
1"
#810000
0"
#811000
b110001100 -
1"
#812000
0"
#813000
b110001101 -
1"
#814000
0"
#815000
b110001110 -
1"
#816000
0"
#817000
b110001111 -
1"
#818000
0"
#819000
b110010000 -
1"
#820000
0"
#821000
b110010001 -
1"
#822000
0"
#823000
b110010010 -
1"
#824000
0"
#825000
b110010011 -
1"
#826000
0"
#827000
b110010100 -
1"
#828000
0"
#829000
b110010101 -
1"
#830000
0"
#831000
b110010110 -
1"
#832000
0"
#833000
b110010111 -
1"
#834000
0"
#835000
b110011000 -
1"
#836000
0"
#837000
b110011001 -
1"
#838000
0"
#839000
b110011010 -
1"
#840000
0"
#841000
b110011011 -
1"
#842000
0"
#843000
b110011100 -
1"
#844000
0"
#845000
b110011101 -
1"
#846000
0"
#847000
b110011110 -
1"
#848000
0"
#849000
b110011111 -
1"
#850000
0"
#851000
b110100000 -
1"
#852000
0"
#853000
b110100001 -
1"
#854000
0"
#855000
b110100010 -
1"
#856000
0"
#857000
b110100011 -
1"
#858000
0"
#859000
b110100100 -
1"
#860000
0"
#861000
b110100101 -
1"
#862000
0"
#863000
b110100110 -
1"
#864000
0"
#865000
b110100111 -
1"
#866000
0"
