UNDron_matrix/rtl/wb_mulspi/mulspi/spi_master.v
///////////////////////////////////////////////////////////////////////////////////////////////////////////////////////
//FileName: spi_master.v
//code: verilog.
//Developed: Scott Larson.
//translator: engineer training Julk N.
//Data: 8/july/2016.
//Note: Module for manage a spi_master module, Translated from VHDL code of Scott Larson Larson, see web page https://eewiki.net/pages/viewpage.action?pageId=4096079.
//More Info: https://eewiki.net/pages/viewpage.action?pageId=4096079  or in this folder
//Special Thanks: Scott Larson.
//University: National University of Colombia.
///////////////////////////////////////////////////////////////////////////////////////////////////////////////////////


module spi_master(clk, rst, enable, cpol, cpha, cont, clk_div, addr, tx_data, miso, sclk, ss_n, mosi, busy, rx_data);


/*
                   ______________
 clk      ------->|              |-------> busy            |
 rst      ------->|              |-------> sclk            |
 cpol     ------->|              |-------> ss_n            |
 cpha     ------->|              |												 |CONTROL SIGNALS 
 cont     ------->|              |												 |
 enable   ------->|  spi_master  |												 |
                  |              |
 clk_div  ------->|              |
 addr     ------->|              |
 miso     ------->|              |-------> mosi            |DATA SIGNALS
 tx_data     ---->|______________|-------> rx_data         |

*/
//--------------------------------------------------------
//Parametros de construccion
//--------------------------------------------------------
  parameter slaves = 4; //number of spi_slave
  parameter d_width = 8; //data bus data width
//--------------------------------------------------------
//Entradas y salidas del modulo
//--------------------------------------------------------
  input clk, rst, enable, cpol, cpha, cont, miso;
  input [d_width-1:0] tx_data;
  input [31:0] clk_div;
  input [31:0] addr;
  output reg mosi,busy;
  output reg sclk = 1'b0;
  output reg [slaves-1:0] ss_n;
  output reg [d_width-1:0] rx_data;
//--------------------------------------------------------
//Parametros y registros internos requeridos por el modulo
//--------------------------------------------------------
  
  parameter ready   =2'b01;               //|
  parameter execute =2'b10;               //|State machine data type

  reg [1:0] state;                        //Current State
  reg [31:0] slave = 31'b0;               //slave selected for current transaction
  reg [31:0] clk_ratio = 31'b0;           //current clk_div
  reg [31:0] count = 31'b0;               //counter to trigger sclk from system clock
  reg [d_width*2+1:0] clk_toggles = 0;    //count spi clock toggles
  reg assert_data;                        //1'b1 is tx sclk toggle, 1'b0 is rx sclk toggle
  reg continue = 1'b0;                    //flag to continue transaction
  reg [d_width-1:0] rx_buffer = 0;        //receive data buffer
  reg [d_width-1:0] tx_buffer = 0;        //transmit data buffer
  reg [d_width*2:0] last_bit_rx = 0;      //last rx data bit location

  always @(posedge clk, posedge rst) begin
  if (rst) begin
    busy <=1'b1;
    ss_n <= {(slaves){1'b1}};
    mosi <= 1'bz;
    rx_data <=0;
    state <= ready;
  end
  else begin  
    case(state)
      ready: begin
        busy <= 1'b0;
        ss_n <= {(slaves){1'b1}};
        mosi <= 1'bz;
        continue <= 1'b0;
				//user input to initiate transaction
        if (enable) begin
          busy <= 1'b1;
          if (addr < slaves) begin
            slave <= addr;
          end else begin
            slave <= 0;
          end
					if (clk_div == 1'b0) begin
						clk_ratio <= 1;
						count <= 1;
					end else begin
					  clk_ratio <= clk_div;
					  count <= clk_div;
				  end
          sclk <= cpol;
          assert_data <= !cpha;
          tx_buffer <= tx_data;
					clk_toggles <= 0;
					last_bit_rx <= d_width*2 + cpha - 1;
					state <= execute;
        end 
        else begin
          state <= ready;
        end
      end

      execute: begin
		    ss_n [slave] <= 1'b0;	
				busy <= 1'b1;
		    if (count == clk_ratio) begin
					count <= 1;
					assert_data <= !assert_data;
					if (clk_toggles == d_width*2+1) 
		      	clk_toggles <= 0;
		      else
		 				clk_toggles <= clk_toggles+1; //{{(d_width*2){1'b0}},1'b1}
				
					if ((clk_toggles <= d_width*2) && (ss_n[slave]==1'b0)) begin
						sclk <= !sclk;
					end

					if ((assert_data == 1'b0) && (clk_toggles < last_bit_rx+1) && (ss_n[slave]==1'b0)) begin
						rx_buffer <= {rx_buffer[d_width-2:0], miso};
		      end

					if ((assert_data == 1'b1) && (clk_toggles< last_bit_rx)) begin
						mosi <= tx_buffer[d_width-1];
						tx_buffer <= {tx_buffer[d_width-2:0],1'b0};
		      end
		     
					if ((clk_toggles == last_bit_rx) && (cont == 1'b1)) begin
						tx_buffer <= tx_data;
		        clk_toggles <= last_bit_rx - d_width*2+1;
						continue <= 1'b1; 	
		      end

					if(continue) begin
						continue <= 1'b0;
						busy <= 1'b0;
						rx_data <= rx_buffer;
		      end

					if((clk_toggles == d_width*2+1) && (cont == 1'b0)) begin
						busy <=1'b0;
						ss_n <= {(slaves){1'b1}};
						mosi <= 1'bz;
						rx_data <= rx_buffer;
						state <= ready;
		      end
					else begin
		  			state <= execute;
					end
				end
				else begin
					count <= count+1; //{{(30){1'b0}},1'b1}
					state <= execute;
		    end
		  end
		endcase
	end
end 
endmodule

UNDron_matrix/rtl/wb_mulspi/mulspi/spi_master_TB.v
`timescale 1ns / 1ps
`define SIMULATION

module spi_master_TB;

	parameter slaves = 4;
	parameter d_width = 8;

  reg clk, rst, enable, cpol, cpha, cont, miso;
  reg [d_width-1:0] tx_data;
  reg [31:0] clk_div;
  reg [31:0] addr;
  reg [0:(d_width-1)] miso_data;
	reg mode;
  wire sclk1;
  wire ss;
	reg [d_width-1:0] count_t;
  wire mosi, sclk, busy;
  wire [slaves-1:0] ss_n;
  wire [d_width-1:0] rx_data;

spi_master uut(.clk(clk), .rst(rst), .enable(enable), .cpol(cpol), .cpha(cpha), .cont(cont), .clk_div(clk_div), .addr(addr), .tx_data(tx_data), .miso(miso), .sclk(sclk), .ss_n(ss_n), .mosi(mosi), .busy(busy), .rx_data(rx_data));

initial begin

	clk = 1'b0;
	rst = 1'b0;
	enable = 1'b0;
	cpol = 1'b1;
	cpha = 1'b1;
	cont = 1'b1;
	miso = 1'bz;
	tx_data = 8'b00011101;
	clk_div = 5;
	addr = 3;
	miso_data = 8'b01010101;
	mode = !(cpha + cpol);
  count_t = 0;

end 

assign ss = ss_n[addr];
always clk = #5 ~clk;   //100MHz
//always clk = #10 ~clk;    //50MHz	

assign sclk1 = (mode) ? !sclk : sclk;

	always @(negedge ss) begin
		if(!cpha) begin
			miso <= miso_data[count_t];
		  count_t = count_t+1;
    end
		else begin
			count_t  = 0;
		end
 end 

	always @(posedge sclk1, posedge ss) begin
		
		if(count_t == d_width) begin
			if(cont) begin
				//tx_data <= 8'b1;
				miso_data = 8'b0;
				count_t = 0;
			end else
      begin
        miso <= 1'bz;
      end
    end else
    if (!ss)begin
			miso <= miso_data[count_t];
			count_t = count_t + 1;
		end
	end

	always @(negedge busy) begin
		if(!ss)begin
			tx_data = 8'b1;
		end
	end

  initial begin: TEST_CASE
      $dumpfile("spi_master_TB.vcd");
      $dumpvars(0, spi_master_TB);
      #5 rst = 1'b1;
      #5 rst = 1'b0;
      #10 enable = 1'b1;
      #10 enable = 1'b0;
      #2500 cont = 1'b0;
      #100 $finish;
  end 
endmodule

UNDron_matrix/rtl/wb_mulspi/mulspi/simulation/spi_master_TB.vcd
$date
	Tue Sep 20 22:56:26 2016
$end
$version
	Icarus Verilog
$end
$timescale
	1ps
$end
$scope module spi_master_TB $end
$var wire 1 ! busy $end
$var wire 1 " mosi $end
$var wire 8 # rx_data [7:0] $end
$var wire 1 $ sclk $end
$var wire 1 % sclk1 $end
$var wire 1 & ss $end
$var wire 4 ' ss_n [3:0] $end
$var reg 32 ( addr [31:0] $end
$var reg 1 ) clk $end
$var reg 32 * clk_div [31:0] $end
$var reg 1 + cont $end
$var reg 8 , count_t [7:0] $end
$var reg 1 - cpha $end
$var reg 1 . cpol $end
$var reg 1 / enable $end
$var reg 1 0 miso $end
$var reg 8 1 miso_data [0:7] $end
$var reg 1 2 mode $end
$var reg 1 3 rst $end
$var reg 8 4 tx_data [7:0] $end
$scope module uut $end
$var wire 32 5 addr [31:0] $end
$var wire 1 6 clk $end
$var wire 32 7 clk_div [31:0] $end
$var wire 1 8 cont $end
$var wire 1 9 cpha $end
$var wire 1 : cpol $end
$var wire 1 ; enable $end
$var wire 1 < miso $end
$var wire 1 = rst $end
$var wire 8 > tx_data [7:0] $end
$var reg 1 ? assert_data $end
$var reg 1 @ busy $end
$var reg 32 A clk_ratio [31:0] $end
$var reg 18 B clk_toggles [17:0] $end
$var reg 1 C continue $end
$var reg 32 D count [31:0] $end
$var reg 17 E last_bit_rx [16:0] $end
$var reg 1 F mosi $end
$var reg 8 G rx_buffer [7:0] $end
$var reg 8 H rx_data [7:0] $end
$var reg 1 I sclk $end
$var reg 32 J slave [31:0] $end
$var reg 4 K ss_n [3:0] $end
$var reg 2 L state [1:0] $end
$var reg 8 M tx_buffer [7:0] $end
$upscope $end
$scope begin TEST_CASE $end
$upscope $end
$upscope $end
$enddefinitions $end
#0
$dumpvars
b0 M
bx L
bx K
b0 J
0I
bx H
b0 G
xF
b0 E
b0 D
0C
b0 B
b0 A
x@
x?
b11101 >
0=
z<
0;
1:
19
18
b101 7
06
b11 5
b11101 4
03
12
b1010101 1
z0
0/
1.
1-
b0 ,
1+
b101 *
0)
b11 (
bx '
x&
1%
0$
bx #
x"
x!
$end
#5000
b1 L
b0 H
b0 #
zF
z"
b1111 K
1&
b1111 '
1@
1!
13
1=
1)
16
#10000
03
0=
0)
06
#15000
0@
0!
1)
16
#20000
0)
06
1/
1;
#25000
0%
b10 L
b10000 E
b11101 M
0?
1I
1$
b101 D
b101 A
b11 J
1@
1!
1)
16
#30000
0)
06
0/
0;
#35000
b1 B
1?
b1 D
b111 K
0&
b111 '
1)
16
#40000
0)
06
#45000
b10 D
b111 K
1)
16
#50000
0)
06
#55000
b11 D
b111 K
1)
16
#60000
0)
06
#65000
b100 D
b111 K
1)
16
#70000
0)
06
#75000
b101 D
b111 K
1)
16
#80000
0)
06
#85000
00
0<
b1 ,
1%
b111010 M
0F
0"
0I
0$
b10 B
0?
b1 D
b111 K
1)
16
#90000
0)
06
#95000
b10 D
b111 K
1)
16
#100000
0)
06
#105000
b11 D
b111 K
1)
16
#110000
0)
06
#115000
b100 D
b111 K
1)
16
#120000
0)
06
#125000
b101 D
b111 K
1)
16
#130000
0)
06
#135000
0%
1I
1$
b11 B
1?
b1 D
b111 K
1)
16
#140000
0)
06
#145000
b10 D
b111 K
1)
16
#150000
0)
06
#155000
b11 D
b111 K
1)
16
#160000
0)
06
#165000
b100 D
b111 K
1)
16
#170000
0)
06
#175000
b101 D
b111 K
1)
16
#180000
0)
06
#185000
10
1<
b10 ,
1%
b1110100 M
0I
0$
b100 B
0?
b1 D
b111 K
1)
16
#190000
0)
06
#195000
b10 D
b111 K
1)
16
#200000
0)
06
#205000
b11 D
b111 K
1)
16
#210000
0)
06
#215000
b100 D
b111 K
1)
16
#220000
0)
06
#225000
b101 D
b111 K
1)
16
#230000
0)
06
#235000
0%
b1 G
1I
1$
b101 B
1?
b1 D
b111 K
1)
16
#240000
0)
06
#245000
b10 D
b111 K
1)
16
#250000
0)
06
#255000
b11 D
b111 K
1)
16
#260000
0)
06
#265000
b100 D
b111 K
1)
16
#270000
0)
06
#275000
b101 D
b111 K
1)
16
#280000
0)
06
#285000
00
0<
b11 ,
1%
b11101000 M
0I
0$
b110 B
0?
b1 D
b111 K
1)
16
#290000
0)
06
#295000
b10 D
b111 K
1)
16
#300000
0)
06
#305000
b11 D
b111 K
1)
16
#310000
0)
06
#315000
b100 D
b111 K
1)
16
#320000
0)
06
#325000
b101 D
b111 K
1)
16
#330000
0)
06
#335000
0%
b10 G
1I
1$
b111 B
1?
b1 D
b111 K
1)
16
#340000
0)
06
#345000
b10 D
b111 K
1)
16
#350000
0)
06
#355000
b11 D
b111 K
1)
16
#360000
0)
06
#365000
b100 D
b111 K
1)
16
#370000
0)
06
#375000
b101 D
b111 K
1)
16
#380000
0)
06
#385000
10
1<
b100 ,
1%
b11010000 M
1F
1"
0I
0$
b1000 B
0?
b1 D
b111 K
1)
16
#390000
0)
06
#395000
b10 D
b111 K
1)
16
#400000
0)
06
#405000
b11 D
b111 K
1)
16
#410000
0)
06
#415000
b100 D
b111 K
1)
16
#420000
0)
06
#425000
b101 D
b111 K
1)
16
#430000
0)
06
#435000
0%
b101 G
1I
1$
b1001 B
1?
b1 D
b111 K
1)
16
#440000
0)
06
#445000
b10 D
b111 K
1)
16
#450000
0)
06
#455000
b11 D
b111 K
1)
16
#460000
0)
06
#465000
b100 D
b111 K
1)
16
#470000
0)
06
#475000
b101 D
b111 K
1)
16
#480000
0)
06
#485000
00
0<
b101 ,
1%
b10100000 M
0I
0$
b1010 B
0?
b1 D
b111 K
1)
16
#490000
0)
06
#495000
b10 D
b111 K
1)
16
#500000
0)
06
#505000
b11 D
b111 K
1)
16
#510000
0)
06
#515000
b100 D
b111 K
1)
16
#520000
0)
06
#525000
b101 D
b111 K
1)
16
#530000
0)
06
#535000
0%
b1010 G
1I
1$
b1011 B
1?
b1 D
b111 K
1)
16
#540000
0)
06
#545000
b10 D
b111 K
1)
16
#550000
0)
06
#555000
b11 D
b111 K
1)
16
#560000
0)
06
#565000
b100 D
b111 K
1)
16
#570000
0)
06
#575000
b101 D
b111 K
1)
16
#580000
0)
06
#585000
10
1<
b110 ,
1%
b1000000 M
0I
0$
b1100 B
0?
b1 D
b111 K
1)
16
#590000
0)
06
#595000
b10 D
b111 K
1)
16
#600000
0)
06
#605000
b11 D
b111 K
1)
16
#610000
0)
06
#615000
b100 D
b111 K
1)
16
#620000
0)
06
#625000
b101 D
b111 K
1)
16
#630000
0)
06
#635000
0%
b10101 G
1I
1$
b1101 B
1?
b1 D
b111 K
1)
16
#640000
0)
06
#645000
b10 D
b111 K
1)
16
#650000
0)
06
#655000
b11 D
b111 K
1)
16
#660000
0)
06
#665000
b100 D
b111 K
1)
16
#670000
0)
06
#675000
b101 D
b111 K
1)
16
#680000
0)
06
#685000
00
0<
b111 ,
1%
b10000000 M
0F
0"
0I
0$
b1110 B
0?
b1 D
b111 K
1)
16
#690000
0)
06
#695000
b10 D
b111 K
1)
16
#700000
0)
06
#705000
b11 D
b111 K
1)
16
#710000
0)
06
#715000
b100 D
b111 K
1)
16
#720000
0)
06
#725000
b101 D
b111 K
1)
16
#730000
0)
06
#735000
0%
b101010 G
1I
1$
b1111 B
1?
b1 D
b111 K
1)
16
#740000
0)
06
#745000
b10 D
b111 K
1)
16
#750000
0)
06
#755000
b11 D
b111 K
1)
16
#760000
0)
06
#765000
b100 D
b111 K
1)
16
#770000
0)
06
#775000
b101 D
b111 K
1)
16
#780000
0)
06
#785000
10
1<
b1000 ,
1%
b0 M
1F
1"
0I
0$
b10000 B
0?
b1 D
b111 K
1)
16
#790000
0)
06
#795000
b10 D
b111 K
1)
16
#800000
0)
06
#805000
b11 D
b111 K
1)
16
#810000
0)
06
#815000
b100 D
b111 K
1)
16
#820000
0)
06
#825000
b101 D
b111 K
1)
16
#830000
0)
06
#835000
0%
1C
b11101 M
b1010101 G
1I
1$
b1 B
1?
b1 D
b111 K
1)
16
#840000
0)
06
#845000
b10 D
b111 K
1)
16
#850000
0)
06
#855000
b11 D
b111 K
1)
16
#860000
0)
06
#865000
b100 D
b111 K
1)
16
#870000
0)
06
#875000
b101 D
b111 K
1)
16
#880000
0)
06
#885000
b0 ,
b0 1
b1 4
b1 >
1%
b1010101 H
b1010101 #
0@
0!
0C
b111010 M
0F
0"
0I
0$
b10 B
0?
b1 D
b111 K
1)
16
#890000
0)
06
#895000
b10 D
1@
1!
b111 K
1)
16
#900000
0)
06
#905000
b11 D
b111 K
1)
16
#910000
0)
06
#915000
b100 D
b111 K
1)
16
#920000
0)
06
#925000
b101 D
b111 K
1)
16
#930000
0)
06
#935000
0%
b10101011 G
1I
1$
b11 B
1?
b1 D
b111 K
1)
16
#940000
0)
06
#945000
b10 D
b111 K
1)
16
#950000
0)
06
#955000
b11 D
b111 K
1)
16
#960000
0)
06
#965000
b100 D
b111 K
1)
16
#970000
0)
06
#975000
b101 D
b111 K
1)
16
#980000
0)
06
#985000
00
0<
b1 ,
1%
b1110100 M
0I
0$
b100 B
0?
b1 D
b111 K
1)
16
#990000
0)
06
#995000
b10 D
b111 K
1)
16
#1000000
0)
06
#1005000
b11 D
b111 K
1)
16
#1010000
0)
06
#1015000
b100 D
b111 K
1)
16
#1020000
0)
06
#1025000
b101 D
b111 K
1)
16
#1030000
0)
06
#1035000
0%
b1010110 G
1I
1$
b101 B
1?
b1 D
b111 K
1)
16
#1040000
0)
06
#1045000
b10 D
b111 K
1)
16
#1050000
0)
06
#1055000
b11 D
b111 K
1)
16
#1060000
0)
06
#1065000
b100 D
b111 K
1)
16
#1070000
0)
06
#1075000
b101 D
b111 K
1)
16
#1080000
0)
06
#1085000
b10 ,
1%
b11101000 M
0I
0$
b110 B
0?
b1 D
b111 K
1)
16
#1090000
0)
06
#1095000
b10 D
b111 K
1)
16
#1100000
0)
06
#1105000
b11 D
b111 K
1)
16
#1110000
0)
06
#1115000
b100 D
b111 K
1)
16
#1120000
0)
06
#1125000
b101 D
b111 K
1)
16
#1130000
0)
06
#1135000
0%
b10101100 G
1I
1$
b111 B
1?
b1 D
b111 K
1)
16
#1140000
0)
06
#1145000
b10 D
b111 K
1)
16
#1150000
0)
06
#1155000
b11 D
b111 K
1)
16
#1160000
0)
06
#1165000
b100 D
b111 K
1)
16
#1170000
0)
06
#1175000
b101 D
b111 K
1)
16
#1180000
0)
06
#1185000
b11 ,
1%
b11010000 M
1F
1"
0I
0$
b1000 B
0?
b1 D
b111 K
1)
16
#1190000
0)
06
#1195000
b10 D
b111 K
1)
16
#1200000
0)
06
#1205000
b11 D
b111 K
1)
16
#1210000
0)
06
#1215000
b100 D
b111 K
1)
16
#1220000
0)
06
#1225000
b101 D
b111 K
1)
16
#1230000
0)
06
#1235000
0%
b1011000 G
1I
1$
b1001 B
1?
b1 D
b111 K
1)
16
#1240000
0)
06
#1245000
b10 D
b111 K
1)
16
#1250000
0)
06
#1255000
b11 D
b111 K
1)
16
#1260000
0)
06
#1265000
b100 D
b111 K
1)
16
#1270000
0)
06
#1275000
b101 D
b111 K
1)
16
#1280000
0)
06
#1285000
b100 ,
1%
b10100000 M
0I
0$
b1010 B
0?
b1 D
b111 K
1)
16
#1290000
0)
06
#1295000
b10 D
b111 K
1)
16
#1300000
0)
06
#1305000
b11 D
b111 K
1)
16
#1310000
0)
06
#1315000
b100 D
b111 K
1)
16
#1320000
0)
06
#1325000
b101 D
b111 K
1)
16
#1330000
0)
06
#1335000
0%
b10110000 G
1I
1$
b1011 B
1?
b1 D
b111 K
1)
16
#1340000
0)
06
#1345000
b10 D
b111 K
1)
16
#1350000
0)
06
#1355000
b11 D
b111 K
1)
16
#1360000
0)
06
#1365000
b100 D
b111 K
1)
16
#1370000
0)
06
#1375000
b101 D
b111 K
1)
16
#1380000
0)
06
#1385000
b101 ,
1%
b1000000 M
0I
0$
b1100 B
0?
b1 D
b111 K
1)
16
#1390000
0)
06
#1395000
b10 D
b111 K
1)
16
#1400000
0)
06
#1405000
b11 D
b111 K
1)
16
#1410000
0)
06
#1415000
b100 D
b111 K
1)
16
#1420000
0)
06
#1425000
b101 D
b111 K
1)
16
#1430000
0)
06
#1435000
0%
b1100000 G
1I
1$
b1101 B
1?
b1 D
b111 K
1)
16
#1440000
0)
06
#1445000
b10 D
b111 K
1)
16
#1450000
0)
06
#1455000
b11 D
b111 K
1)
16
#1460000
0)
06
#1465000
b100 D
b111 K
1)
16
#1470000
0)
06
#1475000
b101 D
b111 K
1)
16
#1480000
0)
06
#1485000
b110 ,
1%
b10000000 M
0F
0"
0I
0$
b1110 B
0?
b1 D
b111 K
1)
16
#1490000
0)
06
#1495000
b10 D
b111 K
1)
16
#1500000
0)
06
#1505000
b11 D
b111 K
1)
16
#1510000
0)
06
#1515000
b100 D
b111 K
1)
16
#1520000
0)
06
#1525000
b101 D
b111 K
1)
16
#1530000
0)
06
#1535000
0%
b11000000 G
1I
1$
b1111 B
1?
b1 D
b111 K
1)
16
#1540000
0)
06
#1545000
b10 D
b111 K
1)
16
#1550000
0)
06
#1555000
b11 D
b111 K
1)
16
#1560000
0)
06
#1565000
b100 D
b111 K
1)
16
#1570000
0)
06
#1575000
b101 D
b111 K
1)
16
#1580000
0)
06
#1585000
b111 ,
1%
b0 M
1F
1"
0I
0$
b10000 B
0?
b1 D
b111 K
1)
16
#1590000
0)
06
#1595000
b10 D
b111 K
1)
16
#1600000
0)
06
#1605000
b11 D
b111 K
1)
16
#1610000
0)
06
#1615000
b100 D
b111 K
1)
16
#1620000
0)
06
#1625000
b101 D
b111 K
1)
16
#1630000
0)
06
#1635000
0%
1C
b1 M
b10000000 G
1I
1$
b1 B
1?
b1 D
b111 K
1)
16
#1640000
0)
06
#1645000
b10 D
b111 K
1)
16
#1650000
0)
06
#1655000
b11 D
b111 K
1)
16
#1660000
0)
06
#1665000
b100 D
b111 K
1)
16
#1670000
0)
06
#1675000
b101 D
b111 K
1)
16
#1680000
0)
06
#1685000
b1000 ,
1%
b10000000 H
b10000000 #
0@
0!
0C
b10 M
0F
0"
0I
0$
b10 B
0?
b1 D
b111 K
1)
16
#1690000
0)
06
#1695000
b10 D
1@
1!
b111 K
1)
16
#1700000
0)
06
#1705000
b11 D
b111 K
1)
16
#1710000
0)
06
#1715000
b100 D
b111 K
1)
16
#1720000
0)
06
#1725000
b101 D
b111 K
1)
16
#1730000
0)
06
#1735000
0%
b0 G
1I
1$
b11 B
1?
b1 D
b111 K
1)
16
#1740000
0)
06
#1745000
b10 D
b111 K
1)
16
#1750000
0)
06
#1755000
b11 D
b111 K
1)
16
#1760000
0)
06
#1765000
b100 D
b111 K
1)
16
#1770000
0)
06
#1775000
b101 D
b111 K
1)
16
#1780000
0)
06
#1785000
b0 ,
1%
b100 M
0I
0$
b100 B
0?
b1 D
b111 K
1)
16
#1790000
0)
06
#1795000
b10 D
b111 K
1)
16
#1800000
0)
06
#1805000
b11 D
b111 K
1)
16
#1810000
0)
06
#1815000
b100 D
b111 K
1)
16
#1820000
0)
06
#1825000
b101 D
b111 K
1)
16
#1830000
0)
06
#1835000
0%
1I
1$
b101 B
1?
b1 D
b111 K
1)
16
#1840000
0)
06
#1845000
b10 D
b111 K
1)
16
#1850000
0)
06
#1855000
b11 D
b111 K
1)
16
#1860000
0)
06
#1865000
b100 D
b111 K
1)
16
#1870000
0)
06
#1875000
b101 D
b111 K
1)
16
#1880000
0)
06
#1885000
b1 ,
1%
b1000 M
0I
0$
b110 B
0?
b1 D
b111 K
1)
16
#1890000
0)
06
#1895000
b10 D
b111 K
1)
16
#1900000
0)
06
#1905000
b11 D
b111 K
1)
16
#1910000
0)
06
#1915000
b100 D
b111 K
1)
16
#1920000
0)
06
#1925000
b101 D
b111 K
1)
16
#1930000
0)
06
#1935000
0%
1I
1$
b111 B
1?
b1 D
b111 K
1)
16
#1940000
0)
06
#1945000
b10 D
b111 K
1)
16
#1950000
0)
06
#1955000
b11 D
b111 K
1)
16
#1960000
0)
06
#1965000
b100 D
b111 K
1)
16
#1970000
0)
06
#1975000
b101 D
b111 K
1)
16
#1980000
0)
06
#1985000
b10 ,
1%
b10000 M
0I
0$
b1000 B
0?
b1 D
b111 K
1)
16
#1990000
0)
06
#1995000
b10 D
b111 K
1)
16
#2000000
0)
06
#2005000
b11 D
b111 K
1)
16
#2010000
0)
06
#2015000
b100 D
b111 K
1)
16
#2020000
0)
06
#2025000
b101 D
b111 K
1)
16
#2030000
0)
06
#2035000
0%
1I
1$
b1001 B
1?
b1 D
b111 K
1)
16
#2040000
0)
06
#2045000
b10 D
b111 K
1)
16
#2050000
0)
06
#2055000
b11 D
b111 K
1)
16
#2060000
0)
06
#2065000
b100 D
b111 K
1)
16
#2070000
0)
06
#2075000
b101 D
b111 K
1)
16
#2080000
0)
06
#2085000
b11 ,
1%
b100000 M
0I
0$
b1010 B
0?
b1 D
b111 K
1)
16
#2090000
0)
06
#2095000
b10 D
b111 K
1)
16
#2100000
0)
06
#2105000
b11 D
b111 K
1)
16
#2110000
0)
06
#2115000
b100 D
b111 K
1)
16
#2120000
0)
06
#2125000
b101 D
b111 K
1)
16
#2130000
0)
06
#2135000
0%
1I
1$
b1011 B
1?
b1 D
b111 K
1)
16
#2140000
0)
06
#2145000
b10 D
b111 K
1)
16
#2150000
0)
06
#2155000
b11 D
b111 K
1)
16
#2160000
0)
06
#2165000
b100 D
b111 K
1)
16
#2170000
0)
06
#2175000
b101 D
b111 K
1)
16
#2180000
0)
06
#2185000
b100 ,
1%
b1000000 M
0I
0$
b1100 B
0?
b1 D
b111 K
1)
16
#2190000
0)
06
#2195000
b10 D
b111 K
1)
16
#2200000
0)
06
#2205000
b11 D
b111 K
1)
16
#2210000
0)
06
#2215000
b100 D
b111 K
1)
16
#2220000
0)
06
#2225000
b101 D
b111 K
1)
16
#2230000
0)
06
#2235000
0%
1I
1$
b1101 B
1?
b1 D
b111 K
1)
16
#2240000
0)
06
#2245000
b10 D
b111 K
1)
16
#2250000
0)
06
#2255000
b11 D
b111 K
1)
16
#2260000
0)
06
#2265000
b100 D
b111 K
1)
16
#2270000
0)
06
#2275000
b101 D
b111 K
1)
16
#2280000
0)
06
#2285000
b101 ,
1%
b10000000 M
0I
0$
b1110 B
0?
b1 D
b111 K
1)
16
#2290000
0)
06
#2295000
b10 D
b111 K
1)
16
#2300000
0)
06
#2305000
b11 D
b111 K
1)
16
#2310000
0)
06
#2315000
b100 D
b111 K
1)
16
#2320000
0)
06
#2325000
b101 D
b111 K
1)
16
#2330000
0)
06
#2335000
0%
1I
1$
b1111 B
1?
b1 D
b111 K
1)
16
#2340000
0)
06
#2345000
b10 D
b111 K
1)
16
#2350000
0)
06
#2355000
b11 D
b111 K
1)
16
#2360000
0)
06
#2365000
b100 D
b111 K
1)
16
#2370000
0)
06
#2375000
b101 D
b111 K
1)
16
#2380000
0)
06
#2385000
b110 ,
1%
b0 M
1F
1"
0I
0$
b10000 B
0?
b1 D
b111 K
1)
16
#2390000
0)
06
#2395000
b10 D
b111 K
1)
16
#2400000
0)
06
#2405000
b11 D
b111 K
1)
16
#2410000
0)
06
#2415000
b100 D
b111 K
1)
16
#2420000
0)
06
#2425000
b101 D
b111 K
1)
16
#2430000
0)
06
#2435000
0%
1C
b1 M
1I
1$
b1 B
1?
b1 D
b111 K
1)
16
#2440000
0)
06
#2445000
b10 D
b111 K
1)
16
#2450000
0)
06
#2455000
b11 D
b111 K
1)
16
#2460000
0)
06
#2465000
b100 D
b111 K
1)
16
#2470000
0)
06
#2475000
b101 D
b111 K
1)
16
#2480000
0)
06
#2485000
b111 ,
1%
b0 H
b0 #
0@
0!
0C
b10 M
0F
0"
0I
0$
b10 B
0?
b1 D
b111 K
1)
16
#2490000
0)
06
#2495000
b10 D
1@
1!
b111 K
1)
16
#2500000
0)
06
#2505000
b11 D
b111 K
1)
16
#2510000
0)
06
#2515000
b100 D
b111 K
1)
16
#2520000
0)
06
#2525000
b101 D
b111 K
1)
16
#2530000
0)
06
0+
08
#2535000
0%
1I
1$
b11 B
1?
b1 D
b111 K
1)
16
#2540000
0)
06
#2545000
b10 D
b111 K
1)
16
#2550000
0)
06
#2555000
b11 D
b111 K
1)
16
#2560000
0)
06
#2565000
b100 D
b111 K
1)
16
#2570000
0)
06
#2575000
b101 D
b111 K
1)
16
#2580000
0)
06
#2585000
b1000 ,
1%
b100 M
0I
0$
b100 B
0?
b1 D
b111 K
1)
16
#2590000
0)
06
#2595000
b10 D
b111 K
1)
16
#2600000
0)
06
#2605000
b11 D
b111 K
1)
16
#2610000
0)
06
#2615000
b100 D
b111 K
1)
16
#2620000
0)
06
#2625000
b101 D
b111 K
1)
16
