Modulos_individuales/ADC0832/verilog/ADC_READER.v
`timescale 1ns / 1ps
//////////////////////////////////////////////////////////////////////////////////
// Company: 
// Engineer: 
// 
// Create Date:    12:41:34 12/05/2015 
// Design Name: 
// Module Name:    ADC_READER 
// Project Name: 
// Target Devices: 
// Tool versions: 
// Description: 
//
// Dependencies: 
//
// Revision: 
// Revision 0.01 - File Created
// Additional Comments: 
//
//////////////////////////////////////////////////////////////////////////////////
module ADC_READER(ADC_VALUE_PORT, DONE_RD, ADC_READ_PORT, enable, clk);

    output reg [12:0] ADC_VALUE_PORT; //recibe un valor de 8 bits multiplicado por 20 lo que dara un total de 13 bits
    output reg        DONE_RD;
    input             ADC_READ_PORT;
    input             enable;   
    input             clk; 

           reg [2:0] counter;
           reg [7:0] registro;
           reg       activador;

    initial begin
      ADC_VALUE_PORT  = 13'd0;
      DONE_RD         = 0;
      counter         = 3'b000;
      registro       <= 8'b00000000;
      activador       = 1;
    end  
    
     
always @(posedge clk) 

    if (enable==0) 

        begin
        counter         =  3'b000;
        registro       <= 8'b00000000;
        ADC_VALUE_PORT  =  13'd0;
        DONE_RD         =  0;
        activador       =  1;
        end

    else if (enable==1) 

        begin
  
             if(activador==1)
              begin
                 
                  registro<=(registro+ADC_READ_PORT)<<1;
                  ADC_VALUE_PORT=registro;

                 if(counter==3'b111) 
                   begin
                    registro<=registro+ADC_READ_PORT;
                    ADC_VALUE_PORT=registro;
                    activador=0;
                   end

                 counter = counter+1'b1;      
              end

             else if(activador==0)
              begin
                  DONE_RD        = 1;
                  ADC_VALUE_PORT = registro*20;  
              end    
        end

endmodule

Modulos_individuales/ADC0832/verilog/ADC_COMMANDER.v
`timescale 1ns / 1ps
//////////////////////////////////////////////////////////////////////////////////
// Company: 
// Engineer: 
// 
// Create Date:    12:40:41 12/05/2015 
// Design Name: 
// Module Name:    ADC_COMMANDER 
// Project Name: 
// Target Devices: 
// Tool versions: 
// Description: 
//
// Dependencies: 
//
// Revision: 
// Revision 0.01 - File Created
// Additional Comments: 
//
//////////////////////////////////////////////////////////////////////////////////
module ADC_COMMANDER(COMMAND_DATA_PORT, COMMAND_READ, CHANNEL_SELECT, enable, clk );

     output reg       COMMAND_DATA_PORT;
     output reg       COMMAND_READ;
     input            CHANNEL_SELECT;  //correccion
     input            enable;   
     input            clk;

            reg [2:0] counter;
            reg       activador;


    initial begin 
       COMMAND_READ      = 0;
       COMMAND_DATA_PORT = 0;

       counter           = 3'b000;
       activador         = 0;
    end



     
always @(negedge clk)  

    if (enable==0) 

        begin
        counter           = 3'b000;
        COMMAND_DATA_PORT = 1'b0 ;
        COMMAND_READ      = 0;
        activador         = 1;
        end


    else if (enable==1) 

        begin

             if(activador==1)

             begin
                   if(counter==3'b000) 
                     begin
                       COMMAND_DATA_PORT = 1'b1;
                     end

                   if(counter==3'b001) 
                     begin
                       COMMAND_DATA_PORT = 1'b1;
                     end

                  if(counter==3'b010) 
                     begin

                        if (CHANNEL_SELECT==0)
                          begin
                           COMMAND_DATA_PORT = 1'b0;
                          end

                        else if (CHANNEL_SELECT==1)
                          begin
                           COMMAND_DATA_PORT = 1'b1;
                          end

                     end 

                  if(counter==3'b011) 
                     begin
                       COMMAND_DATA_PORT = 1'b0;
                       activador=0;
                     end    
  
                     counter = counter+1'b1;  
             end



             else if(activador==0)

             begin
                  COMMAND_DATA_PORT = 1'b0 ;
                  COMMAND_READ      = 1;

             end
             
        end

endmodule

Modulos_individuales/ADC0832/verilog/MCP0832.v
`timescale 1ns / 1ps
//////////////////////////////////////////////////////////////////////////////////
// Company: 
// Engineer: 
// 
// Create Date:    12:39:53 12/05/2015 
// Design Name: 
// Module Name:    MCP0832 
// Project Name: 
// Target Devices: 
// Tool versions: 
// Description: 
//
// Dependencies: 
//
// Revision: 
// Revision 0.01 - File Created
// Additional Comments: 
//
//////////////////////////////////////////////////////////////////////////////////
module MCP0832(ADC_COMMAND_DATA_PORT, SEL_PIN_PORT, ADC_VALUE_PORT, DONE_RD, CHANNEL_SELECT, ADC_READ_PORT, enable, clk);

  output        ADC_COMMAND_DATA_PORT; // Empleado para programar el ADC fisico
  output reg    SEL_PIN_PORT;          // Este es el que inicializa al ADC fisico (como un enable).
  output [12:0] ADC_VALUE_PORT;        // Es la lectura que obtengo del modulo viene expresada en mV
  output        DONE_RD;               // Indica que la lectura ya fue realizada

  input         CHANNEL_SELECT;        //Funciona para seleccionar el canal debe ser 0 para infrarrojo y 1 para rojo
  input         ADC_READ_PORT;         //Es el puerto donde se realizan las lecturas, se recibe informacion del adc fisico
  input         enable;                //Funciona para habilitar el modulo si es 1 comienza a funcionar, si es cero se resetea el modulo
  input         clk;                   //Pulso de reloj para que el modulo funcione, debe estar conectado a este por medio de un divisor f

  wire W_GO;

//----------------------------------------------------------------------------------------------------------------------------
  ADC_COMMANDER ADC_COMMANDER0 (.COMMAND_DATA_PORT(ADC_COMMAND_DATA_PORT), .COMMAND_READ(W_GO), .CHANNEL_SELECT(CHANNEL_SELECT) , .enable(enable), .clk(clk));
//---------------------------------------------------------------------------------------------------------------------------- 
  ADC_READER ADC_READER0 (.ADC_VALUE_PORT(ADC_VALUE_PORT), .DONE_RD(DONE_RD), .ADC_READ_PORT(ADC_READ_PORT) , .enable(W_GO)  , .clk(clk));
//----------------------------------------------------------------------------------------------------------------------------  
  always @(enable)
  if(enable==1)
   begin
    SEL_PIN_PORT=0;
   end
  else
    SEL_PIN_PORT=1;

endmodule

Modulos_individuales/ADC0832/verilog/MCP0832_TB.v
`timescale 1ns / 1ps

////////////////////////////////////////////////////////////////////////////////
// Company: 
// Engineer:
//
// Create Date:   12:52:52 12/05/2015
// Design Name:   MCP0832
// Module Name:   /home/nixtropy/MCP0832/MCP0832_TB.v
// Project Name:  MCP0832
// Target Device:  
// Tool versions:  
// Description: 
//
// Verilog Test Fixture created by ISE for module: MCP0832
//
// Dependencies:
// 
// Revision:
// Revision 0.01 - File Created
// Additional Comments:
// 
////////////////////////////////////////////////////////////////////////////////

module MCP0832_TB;
/*
------------------------------------
MODULO A PROBAR
------------------------------------

module MCP0832(ADC_COMMAND_DATA_PORT, SEL_PIN_PORT, ADC_VALUE_PORT, DONE_RD, CHANNEL_SELECT, ADC_READ_PORT, enable, clk);
 
SALIDAS  son wires

  output       ADC_COMMAND_DATA_PORT;
  output reg   SEL_PIN_PORT;
  output [12:0] ADC_VALUE_PORT;
  output       DONE_RD;

ENTRADAS son registros

  input        CHANNEL_SELECT;
  input        ADC_READ_PORT;
  input        enable;   
  input        clk; 

*/

// SALIDAS  

  wire ADC_COMMAND_DATA_PORT;
  wire SEL_PIN_PORT;
  wire [12:0] ADC_VALUE_PORT;
  wire DONE_RD;

// ENTRADAS 

  reg CHANNEL_SELECT = 0;
  reg ADC_READ_PORT  = 0;
  reg enable         = 0;   
  reg clk            = 0;
  always #5 clk = !clk; 

  initial begin
     $dumpfile("test.vcd");
     $dumpvars(0,MCP0832_TB);

     # 50 enable = 1;
          CHANNEL_SELECT = 0;   
       #0  ADC_READ_PORT = 0;//ruido
       #10 ADC_READ_PORT = 0;//ruido  
       #10 ADC_READ_PORT = 0;//ruido
       #10 ADC_READ_PORT = 0;//ruido
       #10 ADC_READ_PORT = 0;//catch para verificar 10101010*10100
       #10 ADC_READ_PORT = 0;//catch
       #10 ADC_READ_PORT = 0;//catch 
       #10 ADC_READ_PORT = 0;//catch 
       #10 ADC_READ_PORT = 0;//catch
       #10 ADC_READ_PORT = 0;//catch
       #10 ADC_READ_PORT = 0;//catch
       #10 ADC_READ_PORT = 1;//catch
       #10 ADC_READ_PORT = 0;//ruido 
       #10 ADC_READ_PORT = 0;//ruido
       #10 ADC_READ_PORT = 0;//ruido  
       #10 ADC_READ_PORT = 0;//ruido
       #10 ADC_READ_PORT = 0;//ruido
       #10 ADC_READ_PORT = 0;//ruido
     # 200 enable = 0;
     # 100 enable = 1;
          CHANNEL_SELECT = 1;
       #0  ADC_READ_PORT = 0;//ruido
       #10 ADC_READ_PORT = 0;//ruido  
       #10 ADC_READ_PORT = 0;//ruido
       #10 ADC_READ_PORT = 0;//ruido
       #10 ADC_READ_PORT = 0;//catch para verificar 10101010*10100
       #10 ADC_READ_PORT = 0;//catch
       #10 ADC_READ_PORT = 1;//catch 
       #10 ADC_READ_PORT = 0;//catch 
       #10 ADC_READ_PORT = 1;//catch
       #10 ADC_READ_PORT = 0;//catch
       #10 ADC_READ_PORT = 1;//catch
       #10 ADC_READ_PORT = 1;//catch
       #10 ADC_READ_PORT = 0;//ruido 
       #10 ADC_READ_PORT = 0;//ruido
       #10 ADC_READ_PORT = 0;//ruido  
       #10 ADC_READ_PORT = 0;//ruido
       #10 ADC_READ_PORT = 0;//ruido
       #10 ADC_READ_PORT = 0;//ruido
     # 400 $finish;
  end

 

//---------------------------------------------------------------------------------------------------  
  MCP0832 MCP0832f (.ADC_COMMAND_DATA_PORT(ADC_COMMAND_DATA_PORT), .SEL_PIN_PORT(SEL_PIN_PORT), .ADC_VALUE_PORT(ADC_VALUE_PORT), .DONE_RD(DONE_RD), .CHANNEL_SELECT(CHANNEL_SELECT), .ADC_READ_PORT(ADC_READ_PORT), .enable(enable), .clk(clk));
//--------------------------------------------------------------------------------------------------- 

  initial
     $monitor("At time = %t, COMANDO_ADC = %b,CS = %b, SALIDA = %b, DONE = %b, CANAL = %b, DATA_IN = %b,ENABLE = %b, CLK = %b",
              $time, ADC_COMMAND_DATA_PORT, SEL_PIN_PORT, ADC_VALUE_PORT, DONE_RD, CHANNEL_SELECT, ADC_READ_PORT, enable, clk);
endmodule // test

Modulos_individuales/ADC0832/verilog/test.vcd
$date
   Thu Dec 10 09:55:07 2015
$end
$version
  P.20131013
$end
$timescale
  1ps
$end
$scope module MCP0832_TB $end
$var wire 1 5 ADC_COMMAND_DATA_PORT $end
$var wire 1 " SEL_PIN_PORT $end
$var wire 1 6 ADC_VALUE_PORT [12] $end
$var wire 1 7 ADC_VALUE_PORT [11] $end
$var wire 1 8 ADC_VALUE_PORT [10] $end
$var wire 1 9 ADC_VALUE_PORT [9] $end
$var wire 1 : ADC_VALUE_PORT [8] $end
$var wire 1 ; ADC_VALUE_PORT [7] $end
$var wire 1 < ADC_VALUE_PORT [6] $end
$var wire 1 = ADC_VALUE_PORT [5] $end
$var wire 1 > ADC_VALUE_PORT [4] $end
$var wire 1 ? ADC_VALUE_PORT [3] $end
$var wire 1 @ ADC_VALUE_PORT [2] $end
$var wire 1 A ADC_VALUE_PORT [1] $end
$var wire 1 B ADC_VALUE_PORT [0] $end
$var wire 1 C DONE_RD $end
$var reg 1 1 CHANNEL_SELECT $end
$var reg 1 2 ADC_READ_PORT $end
$var reg 1 3 enable $end
$var reg 1 4 clk $end
$scope module MCP0832f $end
$var wire 1 5 ADC_COMMAND_DATA_PORT $end
$var wire 1 6 ADC_VALUE_PORT [12] $end
$var wire 1 7 ADC_VALUE_PORT [11] $end
$var wire 1 8 ADC_VALUE_PORT [10] $end
$var wire 1 9 ADC_VALUE_PORT [9] $end
$var wire 1 : ADC_VALUE_PORT [8] $end
$var wire 1 ; ADC_VALUE_PORT [7] $end
$var wire 1 < ADC_VALUE_PORT [6] $end
$var wire 1 = ADC_VALUE_PORT [5] $end
$var wire 1 > ADC_VALUE_PORT [4] $end
$var wire 1 ? ADC_VALUE_PORT [3] $end
$var wire 1 @ ADC_VALUE_PORT [2] $end
$var wire 1 A ADC_VALUE_PORT [1] $end
$var wire 1 B ADC_VALUE_PORT [0] $end
$var wire 1 C DONE_RD $end
$var wire 1 J CHANNEL_SELECT $end
$var wire 1 Q ADC_READ_PORT $end
$var wire 1 K enable $end
$var wire 1 S clk $end
$var wire 1 R W_GO $end
$var reg 1 I SEL_PIN_PORT $end
$scope module ADC_COMMANDER0 $end
$var wire 1 J CHANNEL_SELECT $end
$var wire 1 K enable $end
$var wire 1 S clk $end
$var reg 1 M COMMAND_DATA_PORT $end
$var reg 1 N COMMAND_READ $end
$var reg 3 O counter [2:0] $end
$var reg 1 P activador $end
$upscope $end
$scope module ADC_READER0 $end
$var wire 1 Q ADC_READ_PORT $end
$var wire 1 R enable $end
$var wire 1 S clk $end
$var reg 13 T ADC_VALUE_PORT [12:0] $end
$var reg 1 U DONE_RD $end
$var reg 3 V counter [2:0] $end
$var reg 8 W registro [7:0] $end
$var reg 1 X activador $end
$upscope $end
$upscope $end
$upscope $end
$enddefinitions $end
#0
$dumpvars
0B
0?
0>
0J
0K
01
02
03
04
1I
0M
0N
b0 O
1P
b0 T
0U
b0 V
b0 W
1X
0Q
05
0C
08
07
06
0;
0:
09
1"
0A
0@
0=
0<
0R
0S
$end
#5000
14
1S
#10000
04
0S
#15000
14
1S
#20000
04
0S
#25000
14
1S
#30000
04
0S
#35000
14
1S
#40000
04
0S
#45000
14
1S
#50000
1K
13
04
0I
1M
b1 O
15
0"
0S
#55000
14
1S
#60000
04
b10 O
0S
#65000
14
1S
#70000
04
0M
b11 O
05
0S
#75000
14
1S
#80000
04
b100 O
0P
0S
#85000
14
1S
#90000
04
1N
1R
0S
#95000
14
b1 V
1S
#100000
04
0S
#105000
14
b10 V
1S
#110000
04
0S
#115000
14
b11 V
1S
#120000
04
0S
#125000
14
b100 V
1S
#130000
04
0S
#135000
14
b101 V
1S
#140000
04
0S
#145000
14
b110 V
1S
#150000
04
0S
#155000
14
b111 V
1S
#160000
12
04
1Q
0S
#165000
14
b0 V
b1 W
0X
1S
#170000
02
04
0Q
0S
#175000
1>
14
b10100 T
1U
1C
1@
1S
